AUTHORS
CONTRIBUTING.md
ChangeLog
LICENSE.txt
README.md
rabbit.yaml
requirements.txt
setup.cfg
setup.py
test-requirements.txt
tox.ini
data/example.yaml
rabbit/__init__.py
rabbit/app.py
rabbit/cli.py
rabbit/command.py
rabbit/config.py
rabbit/display.py
rabbit/flags.py
rabbit/group.py
rabbit/settings.py
rabbit.egg-info/PKG-INFO
rabbit.egg-info/SOURCES.txt
rabbit.egg-info/dependency_links.txt
rabbit.egg-info/entry_points.txt
rabbit.egg-info/not-zip-safe
rabbit.egg-info/pbr.json
rabbit.egg-info/requires.txt
rabbit.egg-info/top_level.txt
tests/__init__.py
tests/test_app.py
tests/test_command.py
tests/test_config.py
tests/test_display.py
tests/test_group.py