Metadata-Version: 1.1
Name: rabbit
Version: 0.0.1.dev58
Summary: Command Line Hopper/Proxy
Home-page: UNKNOWN
Author: Toby Harris
Author-email: tobyharris93@gmail.com
License: UNKNOWN
Keywords: setup
Platform: UNKNOWN
Classifier: Development Status :: 4 - Beta
Classifier: Environment :: Console
Classifier: Intended Audience :: Developers
Classifier: Intended Audience :: Information Technology
Classifier: Operating System :: OS Independent
Classifier: Programming Language :: Python
